common/__init__.py
common/utils.py
databricks_pipelines-0.2.8.dist-info/licenses/LICENSE
databricks_pipelines-0.2.8.dist-info/METADATA
databricks_pipelines-0.2.8.dist-info/WHEEL
databricks_pipelines-0.2.8.dist-info/top_level.txt
databricks_pipelines-0.2.8.dist-info/RECORD
