Metadata-Version: 2.4
Name: databricks-pipelines
Version: 0.2.8
Summary: Modular Databricks pipelines with common, mock, and bronze layers
Author-email: Bruce Jenks <brucejenks@live.com>
License: MIT
Keywords: databricks,pyspark,pipelines,delta,azure
Classifier: Programming Language :: Python :: 3
Classifier: License :: OSI Approved :: MIT License
Classifier: Operating System :: OS Independent
Requires-Python: >=3.8
License-File: LICENSE
Dynamic: license-file
